{"dependencies":[{"name":"/home/kiifox/Documents/projects/portfolio/node_modules/nanohref/package.json","includedInParent":true,"mtime":1530827544100},{"name":"/home/kiifox/Documents/projects/portfolio/package.json","includedInParent":true,"mtime":1530828980612},{"name":"assert","loc":{"line":1,"column":21},"parent":"/home/kiifox/Documents/projects/portfolio/node_modules/nanohref/index.js","resolved":"/home/kiifox/Documents/projects/portfolio/node_modules/nanoassert/index.js"}],"generated":{"js":"var assert = require('assert')\n\nvar safeExternalLink = /(noopener|noreferrer) (noopener|noreferrer)/\nvar protocolLink = /^[\\w-_]+:/\n\nmodule.exports = href\n\nfunction href (cb, root) {\n  assert.notEqual(typeof window, 'undefined', 'nanohref: expected window to exist')\n\n  root = root || window.document\n\n  assert.equal(typeof cb, 'function', 'nanohref: cb should be type function')\n  assert.equal(typeof root, 'object', 'nanohref: root should be type object')\n\n  window.addEventListener('click', function (e) {\n    if ((e.button && e.button !== 0) ||\n      e.ctrlKey || e.metaKey || e.altKey || e.shiftKey ||\n      e.defaultPrevented) return\n\n    var anchor = (function traverse (node) {\n      if (!node || node === root) return\n      if (node.localName !== 'a' || node.href === undefined) {\n        return traverse(node.parentNode)\n      }\n      return node\n    })(e.target)\n\n    if (!anchor) return\n\n    if (window.location.protocol !== anchor.protocol ||\n        window.location.hostname !== anchor.hostname ||\n        window.location.port !== anchor.port ||\n      anchor.hasAttribute('download') ||\n      (anchor.getAttribute('target') === '_blank' &&\n        safeExternalLink.test(anchor.getAttribute('rel'))) ||\n      protocolLink.test(anchor.getAttribute('href'))) return\n\n    e.preventDefault()\n    cb(anchor)\n  })\n}\n","map":{"mappings":[{"source":"node_modules/nanohref/index.js","original":{"line":1,"column":0},"generated":{"line":1,"column":0}},{"source":"node_modules/nanohref/index.js","original":{"line":2,"column":0},"generated":{"line":2,"column":0}},{"source":"node_modules/nanohref/index.js","original":{"line":3,"column":0},"generated":{"line":3,"column":0}},{"source":"node_modules/nanohref/index.js","original":{"line":4,"column":0},"generated":{"line":4,"column":0}},{"source":"node_modules/nanohref/index.js","original":{"line":5,"column":0},"generated":{"line":5,"column":0}},{"source":"node_modules/nanohref/index.js","original":{"line":6,"column":0},"generated":{"line":6,"column":0}},{"source":"node_modules/nanohref/index.js","original":{"line":7,"column":0},"generated":{"line":7,"column":0}},{"source":"node_modules/nanohref/index.js","original":{"line":8,"column":0},"generated":{"line":8,"column":0}},{"source":"node_modules/nanohref/index.js","original":{"line":9,"column":0},"generated":{"line":9,"column":0}},{"source":"node_modules/nanohref/index.js","original":{"line":10,"column":0},"generated":{"line":10,"column":0}},{"source":"node_modules/nanohref/index.js","original":{"line":11,"column":0},"generated":{"line":11,"column":0}},{"source":"node_modules/nanohref/index.js","original":{"line":12,"column":0},"generated":{"line":12,"column":0}},{"source":"node_modules/nanohref/index.js","original":{"line":13,"column":0},"generated":{"line":13,"column":0}},{"source":"node_modules/nanohref/index.js","original":{"line":14,"column":0},"generated":{"line":14,"column":0}},{"source":"node_modules/nanohref/index.js","original":{"line":15,"column":0},"generated":{"line":15,"column":0}},{"source":"node_modules/nanohref/index.js","original":{"line":16,"column":0},"generated":{"line":16,"column":0}},{"source":"node_modules/nanohref/index.js","original":{"line":17,"column":0},"generated":{"line":17,"column":0}},{"source":"node_modules/nanohref/index.js","original":{"line":18,"column":0},"generated":{"line":18,"column":0}},{"source":"node_modules/nanohref/index.js","original":{"line":19,"column":0},"generated":{"line":19,"column":0}},{"source":"node_modules/nanohref/index.js","original":{"line":20,"column":0},"generated":{"line":20,"column":0}},{"source":"node_modules/nanohref/index.js","original":{"line":21,"column":0},"generated":{"line":21,"column":0}},{"source":"node_modules/nanohref/index.js","original":{"line":22,"column":0},"generated":{"line":22,"column":0}},{"source":"node_modules/nanohref/index.js","original":{"line":23,"column":0},"generated":{"line":23,"column":0}},{"source":"node_modules/nanohref/index.js","original":{"line":24,"column":0},"generated":{"line":24,"column":0}},{"source":"node_modules/nanohref/index.js","original":{"line":25,"column":0},"generated":{"line":25,"column":0}},{"source":"node_modules/nanohref/index.js","original":{"line":26,"column":0},"generated":{"line":26,"column":0}},{"source":"node_modules/nanohref/index.js","original":{"line":27,"column":0},"generated":{"line":27,"column":0}},{"source":"node_modules/nanohref/index.js","original":{"line":28,"column":0},"generated":{"line":28,"column":0}},{"source":"node_modules/nanohref/index.js","original":{"line":29,"column":0},"generated":{"line":29,"column":0}},{"source":"node_modules/nanohref/index.js","original":{"line":30,"column":0},"generated":{"line":30,"column":0}},{"source":"node_modules/nanohref/index.js","original":{"line":31,"column":0},"generated":{"line":31,"column":0}},{"source":"node_modules/nanohref/index.js","original":{"line":32,"column":0},"generated":{"line":32,"column":0}},{"source":"node_modules/nanohref/index.js","original":{"line":33,"column":0},"generated":{"line":33,"column":0}},{"source":"node_modules/nanohref/index.js","original":{"line":34,"column":0},"generated":{"line":34,"column":0}},{"source":"node_modules/nanohref/index.js","original":{"line":35,"column":0},"generated":{"line":35,"column":0}},{"source":"node_modules/nanohref/index.js","original":{"line":36,"column":0},"generated":{"line":36,"column":0}},{"source":"node_modules/nanohref/index.js","original":{"line":37,"column":0},"generated":{"line":37,"column":0}},{"source":"node_modules/nanohref/index.js","original":{"line":38,"column":0},"generated":{"line":38,"column":0}},{"source":"node_modules/nanohref/index.js","original":{"line":39,"column":0},"generated":{"line":39,"column":0}},{"source":"node_modules/nanohref/index.js","original":{"line":40,"column":0},"generated":{"line":40,"column":0}},{"source":"node_modules/nanohref/index.js","original":{"line":41,"column":0},"generated":{"line":41,"column":0}},{"source":"node_modules/nanohref/index.js","original":{"line":42,"column":0},"generated":{"line":42,"column":0}},{"source":"node_modules/nanohref/index.js","original":{"line":43,"column":0},"generated":{"line":43,"column":0}}],"sources":{"node_modules/nanohref/index.js":"var assert = require('assert')\n\nvar safeExternalLink = /(noopener|noreferrer) (noopener|noreferrer)/\nvar protocolLink = /^[\\w-_]+:/\n\nmodule.exports = href\n\nfunction href (cb, root) {\n  assert.notEqual(typeof window, 'undefined', 'nanohref: expected window to exist')\n\n  root = root || window.document\n\n  assert.equal(typeof cb, 'function', 'nanohref: cb should be type function')\n  assert.equal(typeof root, 'object', 'nanohref: root should be type object')\n\n  window.addEventListener('click', function (e) {\n    if ((e.button && e.button !== 0) ||\n      e.ctrlKey || e.metaKey || e.altKey || e.shiftKey ||\n      e.defaultPrevented) return\n\n    var anchor = (function traverse (node) {\n      if (!node || node === root) return\n      if (node.localName !== 'a' || node.href === undefined) {\n        return traverse(node.parentNode)\n      }\n      return node\n    })(e.target)\n\n    if (!anchor) return\n\n    if (window.location.protocol !== anchor.protocol ||\n        window.location.hostname !== anchor.hostname ||\n        window.location.port !== anchor.port ||\n      anchor.hasAttribute('download') ||\n      (anchor.getAttribute('target') === '_blank' &&\n        safeExternalLink.test(anchor.getAttribute('rel'))) ||\n      protocolLink.test(anchor.getAttribute('href'))) return\n\n    e.preventDefault()\n    cb(anchor)\n  })\n}\n"},"lineCount":43}},"hash":"fe35ce5e1a91bb98a92cfbc19a9a97d9","cacheData":{"env":{}},"id":29}