{"dependencies":[{"name":"/home/kiifox/Documents/projects/portfolio/node_modules/nanohtml/package.json","includedInParent":true,"mtime":1530827544100},{"name":"/home/kiifox/Documents/projects/portfolio/package.json","includedInParent":true,"mtime":1530828980612}],"generated":{"js":"module.exports = [\n  'autofocus', 'checked', 'defaultchecked', 'disabled', 'formnovalidate',\n  'indeterminate', 'readonly', 'required', 'selected', 'willvalidate'\n]\n","map":{"mappings":[{"source":"node_modules/nanohtml/lib/bool-props.js","original":{"line":1,"column":0},"generated":{"line":1,"column":0}},{"source":"node_modules/nanohtml/lib/bool-props.js","original":{"line":2,"column":0},"generated":{"line":2,"column":0}},{"source":"node_modules/nanohtml/lib/bool-props.js","original":{"line":3,"column":0},"generated":{"line":3,"column":0}},{"source":"node_modules/nanohtml/lib/bool-props.js","original":{"line":4,"column":0},"generated":{"line":4,"column":0}},{"source":"node_modules/nanohtml/lib/bool-props.js","original":{"line":5,"column":0},"generated":{"line":5,"column":0}}],"sources":{"node_modules/nanohtml/lib/bool-props.js":"module.exports = [\n  'autofocus', 'checked', 'defaultchecked', 'disabled', 'formnovalidate',\n  'indeterminate', 'readonly', 'required', 'selected', 'willvalidate'\n]\n"},"lineCount":5}},"hash":"7fa841982c79e89c87a941b3be9b7d78","cacheData":{"env":{}},"id":63}